microphone/__init__.py
microphone/config.py
microphone/configure_input.py
microphone/context_managers.py
week1_test-1.2.1.dist-info/LICENSE
week1_test-1.2.1.dist-info/METADATA
week1_test-1.2.1.dist-info/WHEEL
week1_test-1.2.1.dist-info/top_level.txt
week1_test-1.2.1.dist-info/RECORD
