Metadata-Version: 2.1
Name: week1-test
Version: 1.2.1
Summary: Provides simple interface for recording audio
Home-page: https://github.com/CogWorksBWSI/Microphone
Author: Ryan Soklaski (@rsokl)
Author-email: ry26099@mit.edu
License: MIT
Platform: UNKNOWN
Requires-Python: >=3.6
License-File: LICENSE
Requires-Dist: pyaudio
Requires-Dist: ipython
Requires-Dist: jupyter
Requires-Dist: notebook
Requires-Dist: numpy
Requires-Dist: scipy
Requires-Dist: matplotlib
Requires-Dist: numba
Requires-Dist: librosa
Requires-Dist: ffmpeg
Requires-Dist: mygrad
